README.md
setup.cfg
setup.py
breqwatr_deployment_tool.egg-info/PKG-INFO
breqwatr_deployment_tool.egg-info/SOURCES.txt
breqwatr_deployment_tool.egg-info/dependency_links.txt
breqwatr_deployment_tool.egg-info/entry_points.txt
breqwatr_deployment_tool.egg-info/requires.txt
breqwatr_deployment_tool.egg-info/top_level.txt
bwdt/__init__.py
bwdt/constants.py
bwdt/cli/__init__.py
bwdt/cli/ansible.py
bwdt/cli/apt.py
bwdt/cli/arcus.py
bwdt/cli/ceph.py
bwdt/cli/configure.py
bwdt/cli/docker.py
bwdt/cli/download.py
bwdt/cli/main.py
bwdt/cli/openstack.py
bwdt/cli/pip.py
bwdt/cli/pxe.py
bwdt/cli/registry.py
bwdt/cli/util.py
bwdt/lib/__init__.py
bwdt/lib/auth.py
bwdt/lib/configure.py
bwdt/lib/container.py
bwdt/lib/download.py
bwdt/lib/envvar.py
bwdt/lib/openstack.py
bwdt/lib/aws/__init__.py
bwdt/lib/aws/ecr.py
bwdt/lib/aws/s3.py
bwdt/services/__init__.py
bwdt/services/ansible.py
bwdt/services/apt.py
bwdt/services/arcus.py
bwdt/services/dns.py
bwdt/services/ntp.py
bwdt/services/pip.py
bwdt/services/pxe.py
bwdt/services/registry.py