Metadata-Version: 2.1
Name: breqwatr-deployment-tool
Version: 1.3
Summary: Deploy and manage Breqwatr services
Home-page: https://github.com/breqwatr/breqwatr-deployment-tool
Author: Kyle Pericak
Author-email: kyle@breqwatr.com
License: UNKNOWN
Download-URL: https://github.com/breqwatr/breqwatr-deployment-tool/archive/1.03.tar.gz
Keywords: Breqwatr,Openstack,Kolla
Platform: UNKNOWN
Classifier: Development Status :: 4 - Beta
Classifier: Programming Language :: Python :: 3
Classifier: Natural Language :: English
